odoo/addons/hr_course/README.rst
odoo/addons/hr_course/__init__.py
odoo/addons/hr_course/__manifest__.py
odoo/addons/hr_course/demo/hr_course.xml
odoo/addons/hr_course/i18n/es.po
odoo/addons/hr_course/i18n/hr_course.pot
odoo/addons/hr_course/migrations/13.0.2.0.0/noupdate_changes.xml
odoo/addons/hr_course/migrations/13.0.2.0.0/post-migration.py
odoo/addons/hr_course/migrations/13.0.2.0.0/pre-migration.py
odoo/addons/hr_course/models/__init__.py
odoo/addons/hr_course/models/hr_course.py
odoo/addons/hr_course/models/hr_employee.py
odoo/addons/hr_course/readme/CONTRIBUTORS.rst
odoo/addons/hr_course/readme/DESCRIPTION.rst
odoo/addons/hr_course/readme/USAGE.rst
odoo/addons/hr_course/security/course_security.xml
odoo/addons/hr_course/security/ir.model.access.csv
odoo/addons/hr_course/static/description/icon.png
odoo/addons/hr_course/static/description/index.html
odoo/addons/hr_course/tests/__init__.py
odoo/addons/hr_course/tests/test_hr_course.py
odoo/addons/hr_course/views/hr_course_category_views.xml
odoo/addons/hr_course/views/hr_course_schedule_views.xml
odoo/addons/hr_course/views/hr_course_views.xml
odoo/addons/hr_course/views/hr_employee_views.xml
odoo13_addon_hr_course-13.0.2.1.0.dist-info/METADATA
odoo13_addon_hr_course-13.0.2.1.0.dist-info/WHEEL
odoo13_addon_hr_course-13.0.2.1.0.dist-info/top_level.txt
odoo13_addon_hr_course-13.0.2.1.0.dist-info/RECORD
