Metadata-Version: 2.1
Name: odoo13-addon-hr-course
Version: 13.0.2.1.0
Summary: This module allows your to manage employee's training courses
Home-page: https://github.com/OCA/hr
Author: Creu Blanca,Odoo Community Association (OCA)
Author-email: support@odoo-community.org
License: AGPL-3
Platform: UNKNOWN
Classifier: Programming Language :: Python
Classifier: Framework :: Odoo
Classifier: Framework :: Odoo :: 13.0
Classifier: License :: OSI Approved :: GNU Affero General Public License v3
Requires-Python: >=3.5
Requires-Dist: odoo (<13.1dev,>=13.0a)
